{"id": "ACT475H1S20201", "code": "ACT475H1S", "name": "Insurance Products and Regulation with AXIS", "description": "Examine key types of insurance products and their pricing and valuation. Review representative developments in insurance regulations in US, Europe and Canada. Demonstrate case studies using leading actuarial application AXIS.", "division": "Faculty of Arts and Science", "department": "Statistical Sciences", "prerequisites": "ACT240H1, ACT245H1, ACT247H1", "exclusions": "", "level": 400, "campus": "UTSG", "term": "2020 Winter", "breadths": [5], "meeting_sections": [{"code": "L0101", "instructors": ["V Zhang"], "times": [{"day": "FRIDAY", "start": 50400, "end": 61200, "duration": 10800, "location": "RW 109"}], "size": 25, "enrolment": 23}]}