{"id": "ARC355H1F20199", "code": "ARC355H1F", "name": "History of Urbanism", "description": "A consideration of urbanism through an examination of physical, social, economic, and political factors that have shaped cities and regions from the early modern period up to the present.", "division": "John H. Daniels Faculty of Architecture, Landscape, & Design", "department": "John H. Daniels Faculty of Architecture, Landscape, & Design", "prerequisites": "ARC251H1/ARC252H1/ARC253H1/1.0 FCE in ARC 200+ level lecture courses", "exclusions": "ARC333H1, ARC334H1", "level": 300, "campus": "UTSG", "term": "2019 Fall", "breadths": [], "meeting_sections": [{"code": "L0101", "instructors": ["R Damiani"], "times": [{"day": "THURSDAY", "start": 36000, "end": 43200, "duration": 7200, "location": "SS 1073"}], "size": 100, "enrolment": 0}, {"code": "T0101", "instructors": ["R Damiani"], "times": [{"day": "FRIDAY", "start": 36000, "end": 39600, "duration": 3600, "location": "DA 200"}], "size": 33, "enrolment": 0}, {"code": "T0102", "instructors": ["R Damiani"], "times": [{"day": "FRIDAY", "start": 36000, "end": 39600, "duration": 3600, "location": "DA 230"}], "size": 33, "enrolment": 0}, {"code": "T0103", "instructors": ["R Damiani"], "times": [{"day": "FRIDAY", "start": 36000, "end": 39600, "duration": 3600, "location": "DA 330"}], "size": 34, "enrolment": 0}]}