{"id": "CCT225H5S20201", "code": "CCT225H5S", "name": "Information Systems (DEM)", "description": "This course has been designed to provide students with a basic understanding of the role of computers and communication systems in modern organizations. Unlike programming courses, the focus here is on the application of computer-based systems to support information requirements for problem solving and managerial decision-making. Topics include concepts of information, humans as information processors, survey of hardware and software applications, introduction to information systems analysis and design. [24L, 12T]", "division": "University of Toronto Mississauga", "department": "Institute of Communication and Culture", "prerequisites": "CCT224H5", "exclusions": "CCT325H5; MGM371H5; MGT371H5, RSM327H1, MGAC70H3", "level": 200, "campus": "UTM", "term": "2020 Winter", "breadths": [], "meeting_sections": [{"code": "L0101", "instructors": ["N Al-Hakeem"], "times": [{"day": "WEDNESDAY", "start": 39600, "end": 46800, "duration": 7200, "location": "IB 345"}], "size": 150, "enrolment": 103}, {"code": "T0101", "instructors": [], "times": [{"day": "WEDNESDAY", "start": 46800, "end": 50400, "duration": 3600, "location": "MN 2100"}], "size": 38, "enrolment": 23}, {"code": "T0102", "instructors": [], "times": [{"day": "WEDNESDAY", "start": 46800, "end": 50400, "duration": 3600, "location": "IB 385"}], "size": 38, "enrolment": 33}, {"code": "T0103", "instructors": [], "times": [{"day": "WEDNESDAY", "start": 50400, "end": 54000, "duration": 3600, "location": "MN 2130"}], "size": 37, "enrolment": 13}, {"code": "T0104", "instructors": [], "times": [{"day": "WEDNESDAY", "start": 57600, "end": 61200, "duration": 3600, "location": "IB 260"}], "size": 37, "enrolment": 34}]}