{"id": "CCT273H5S20201", "code": "CCT273H5S", "name": "Professional Practice and Communication", "description": "This professional practice course provides students with basic skills in professional communication, acumen, and problem solving that will help them develop personally and professionally. [24L]", "division": "University of Toronto Mississauga", "department": "Institute of Communication and Culture", "prerequisites": "70% in CCT110H5 or WRI203H5, departmental approval.", "exclusions": "", "level": 200, "campus": "UTM", "term": "2020 Winter", "breadths": [], "meeting_sections": [{"code": "L0101", "instructors": ["T Bowen"], "times": [{"day": "WEDNESDAY", "start": 46800, "end": 54000, "duration": 7200, "location": "IB 280"}], "size": 50, "enrolment": 50}]}