{"id": "CSC324H1F20199", "code": "CSC324H1F", "name": "Principles of Programming Languages", "description": "Programming principles common in modern languages; details of commonly used paradigms. The structure and meaning of code. Scope, control flow, datatypes, and parameter passing. Two non-procedural, non-object-oriented programming paradigms: functional programming (illustrated by languages such as Lisp/Scheme, ML or Haskell) and logic programming (typically illustrated in Prolog).", "division": "Faculty of Arts and Science", "department": "Computer Science", "prerequisites": "CSC263H1/CSC265H1", "exclusions": "NOTE: Students not enrolled in the Computer Science Major or Specialist program at the UTSG, UTM, or UTSC are limited to a maximum of three 300-/400-level CSC/ECE half-courses.", "level": 300, "campus": "UTSG", "term": "2019 Fall", "breadths": [5], "meeting_sections": [{"code": "L0101", "instructors": ["D Liu"], "times": [{"day": "MONDAY", "start": 36000, "end": 39600, "duration": 3600, "location": "GB 248"}, {"day": "WEDNESDAY", "start": 36000, "end": 39600, "duration": 3600, "location": "GB 248"}, {"day": "FRIDAY", "start": 36000, "end": 39600, "duration": 3600, "location": "GB 248"}], "size": 100, "enrolment": 0}, {"code": "L0201", "instructors": ["D Liu"], "times": [{"day": "MONDAY", "start": 39600, "end": 43200, "duration": 3600, "location": "GB 244"}, {"day": "WEDNESDAY", "start": 39600, "end": 43200, "duration": 3600, "location": "GB 244"}, {"day": "FRIDAY", "start": 39600, "end": 43200, "duration": 3600, "location": "GB 244"}], "size": 100, "enrolment": 0}]}