{"id": "ECO419H1F20199", "code": "ECO419H1F", "name": "International Macroeconomics", "description": "This course studies the causes and consequences of international borrowing and lending and exchange rate fluctuations. We will discuss key empirical facts about these phenomena, develop economic models to understand the forces that drive them, and apply the models to gain insights about a variety of historical contexts like China's rapid economic development and the recent sovereign debt crises in the Eurozone periphery.", "division": "Faculty of Arts and Science", "department": "Economics", "prerequisites": "ECO200Y1/ECO204Y1/ECO206Y1, ECO202Y1/ECO208Y1/ECO209Y1, ECO220Y1/ECO227Y1/ (STA220H1, STA255H1)/ (STA237H1, STA238H1)/ (STA257H1, STA261H1)", "exclusions": "", "level": 400, "campus": "UTSG", "term": "2019 Fall", "breadths": [3], "meeting_sections": [{"code": "L0101", "instructors": ["J Steinberg"], "times": [{"day": "WEDNESDAY", "start": 50400, "end": 61200, "duration": 10800, "location": "FE 33"}], "size": 30, "enrolment": 0}]}