{"id": "FAH347H1F20199", "code": "FAH347H1F", "name": "Cubism and Related Movements", "description": "An investigation of the birth and development of Cubism, Futurism and Orphism in Europe and North America.", "division": "Faculty of Arts and Science", "department": "Art History", "prerequisites": "FAH245H1/FAH246H1", "exclusions": "", "level": 300, "campus": "UTSG", "term": "2019 Fall", "breadths": [1], "meeting_sections": [{"code": "L5101", "instructors": ["E Legge"], "times": [{"day": "THURSDAY", "start": 61200, "end": 68400, "duration": 7200, "location": "SS 1071"}], "size": 99, "enrolment": 0}]}