{"id": "FSL105H5S20201", "code": "FSL105H5S", "name": "Functional French-Novice", "description": "The objective of this course, which serves as a starting point in our series of FSL courses, is to introduce students to the phonetic system of the French language, to teach basic vocabulary and to develop awareness of the functions of language in different situations and contexts. An awareness of various francophone cultures and communities will be developed. [36L, 12P]", "division": "University of Toronto Mississauga", "department": "Language Studies", "prerequisites": "", "exclusions": "FSL100H1 or higher. Not open to students who have previously studied French.\u00ffNot open to native speakers of French.", "level": 100, "campus": "UTM", "term": "2020 Winter", "breadths": [], "meeting_sections": [{"code": "L0101", "instructors": ["C Phillips"], "times": [{"day": "MONDAY", "start": 57600, "end": 64800, "duration": 7200, "location": "DV 3131"}], "size": 40, "enrolment": 40}, {"code": "P0101", "instructors": [], "times": [{"day": "WEDNESDAY", "start": 54000, "end": 61200, "duration": 7200, "location": "CC 1160"}], "size": 40, "enrolment": 29}]}