{"id": "GGR357H1S20201", "code": "GGR357H1S", "name": "Housing and Community Development", "description": "Focuses on the importance of adequate housing and quality neighbourhoods. It roots theoretical explanations and policy debates in realities using Canada and Toronto as examples. Topics covered include the evolution of public policies relating to social housing, rental housing, homeownership, neighborhoods, and homelessness.", "division": "Faculty of Arts and Science", "department": "Geography and Planning", "prerequisites": "", "exclusions": "", "level": 300, "campus": "UTSG", "term": "2020 Winter", "breadths": [3], "meeting_sections": [{"code": "L0101", "instructors": ["J Hulchanski"], "times": [{"day": "MONDAY", "start": 54000, "end": 61200, "duration": 7200, "location": "MP 134"}], "size": 60, "enrolment": 60}]}