{"id": "GGR456H1F20199", "code": "GGR456H1F", "name": "Entanglements of Power: Race, Sexuality and the City", "description": "This course investigates the city as a space sculpted by particular configurations and relations of power, and productive of those forms. It considers shifting urban geographies of identity, economy and desire with a focus on race and racism, settler colonialism, empire, the laboring body, sexuality, and sexual identity. Course participants will engage a series of case studies of particular urban spaces and struggles, drawing on conceptual support from scholarship in urban geography, anti-colonial thought, political economy, black studies, feminist and queer theory, Indigenous and settler colonial studies, as well as literature and other artistic work.", "division": "Faculty of Arts and Science", "department": "Geography and Planning", "prerequisites": "10.0 FCEs", "exclusions": "GGR400H1 (Special Topics in Geography I: Entanglements of Power: Race, Sexuality and the City), offered in Fall 2018", "level": 400, "campus": "UTSG", "term": "2019 Fall", "breadths": [3], "meeting_sections": [{"code": "L5101", "instructors": ["D Cowen"], "times": [{"day": "TUESDAY", "start": 61200, "end": 72000, "duration": 10800, "location": "AP 120"}], "size": 30, "enrolment": 0}]}