{"id": "HIS245H1S20201", "code": "HIS245H1S", "name": "European Colonialism, 1700- 1965", "description": "This course will introduce students to the history of European colonialism. It will analyze the nature of colonial rule, the impact of empire on both colonies and metropoles, and delve into questions of power, gender and culture. It considers slavery and abolition, imperial networks, colonial capital, colonial competition, colonial cultures, the twilight of colonial rule, and a variety of settings.", "division": "Faculty of Arts and Science", "department": "History", "prerequisites": "", "exclusions": "HIS389Y0, 20155", "level": 200, "campus": "UTSG", "term": "2020 Winter", "breadths": [3], "meeting_sections": [{"code": "L0101", "instructors": ["E Jennings"], "times": [{"day": "WEDNESDAY", "start": 36000, "end": 43200, "duration": 7200, "location": "VC 323"}], "size": 105, "enrolment": 93}, {"code": "T0101", "instructors": [], "times": [{"day": "WEDNESDAY", "start": 43200, "end": 46800, "duration": 3600, "location": "VC 304"}], "size": 21, "enrolment": 21}, {"code": "T0201", "instructors": [], "times": [{"day": "WEDNESDAY", "start": 46800, "end": 50400, "duration": 3600, "location": "VC 304"}], "size": 21, "enrolment": 21}, {"code": "T0301", "instructors": [], "times": [{"day": "WEDNESDAY", "start": 50400, "end": 54000, "duration": 3600, "location": "NF 009"}], "size": 21, "enrolment": 21}, {"code": "T0401", "instructors": [], "times": [{"day": "WEDNESDAY", "start": 57600, "end": 61200, "duration": 3600, "location": "UC 44"}], "size": 21, "enrolment": 21}, {"code": "T5101", "instructors": [], "times": [{"day": "WEDNESDAY", "start": 61200, "end": 64800, "duration": 3600, "location": "UC 44"}], "size": 15, "enrolment": 4}]}