{"id": "HIS337H1S20201", "code": "HIS337H1S", "name": "Culture, Politics and Society in 18th Century Britain", "description": "Deals with England, Scotland, Ireland and the Atlantic World. Adresses major political, social, economic, intellectual and cultural highlights of the \"long\" eighteenth century. Deals with enlightenment, industrialization and the loss of the first British empire. Interrogates Britain's emerging status as a world power.", "division": "Faculty of Arts and Science", "department": "History", "prerequisites": "", "exclusions": "HIS337Y1", "level": 300, "campus": "UTSG", "term": "2020 Winter", "breadths": [3], "meeting_sections": [{"code": "L0101", "instructors": ["J Mori"], "times": [{"day": "MONDAY", "start": 57600, "end": 61200, "duration": 3600, "location": "UC 161"}, {"day": "WEDNESDAY", "start": 57600, "end": 61200, "duration": 3600, "location": "UC 161"}], "size": 60, "enrolment": 38}]}