{"id": "HPS324H1F20199", "code": "HPS324H1F", "name": "Natural Science and Social Issues", "description": "Historical examination of the interactions of science (both as body of knowledge and as enterprise) with ideological, political and social issues. The impact of science; attacks on and critiques of scientific expertise as background to contemporary conflicts. Subjects may vary according to students interests. (offered irregularly)", "division": "Faculty of Arts and Science", "department": "Inst. for the History & Philosophy of Science & Technology", "prerequisites": "", "exclusions": "", "level": 300, "campus": "UTSG", "term": "2019 Fall", "breadths": [3], "meeting_sections": [{"code": "L0101", "instructors": ["Y Fehige"], "times": [{"day": "THURSDAY", "start": 46800, "end": 54000, "duration": 7200, "location": "CR 403"}], "size": 60, "enrolment": 0}]}