{"id": "IMM385Y1Y20199", "code": "IMM385Y1Y", "name": "Special Research Project in Immunology", "description": "This course provides an opportunity for students to conduct a research project under the supervision of a member of the Faculty. Students are expected to devote a minimum of seven hours per week to the course from the week the fall term lectures begin to the last week of the spring term. Research projects will involve experimental design and work, data analyses, literature reading etc.", "division": "Faculty of Arts and Science", "department": "Immunology", "prerequisites": "IMM250H1", "exclusions": "", "level": 300, "campus": "UTSG", "term": "2019 Fall", "breadths": [4], "meeting_sections": [{"code": "L0101", "instructors": ["A Mortha"], "times": [], "size": 9999, "enrolment": 0}]}