{"id": "INS301Y1Y20199", "code": "INS301Y1Y", "name": "Native Language and Culture", "description": "Examination of the historical interplay of Indigenous languages and cultures in Canada. Particular focus is on the language and culture of an Indigenous people of Ontario.", "division": "Faculty of Arts and Science", "department": "Indigenous Studies Arts & Science", "prerequisites": "5 FCE including INS201Y1, plus one additional INS full course equivalent", "exclusions": "ABS301Y1", "level": 300, "campus": "UTSG", "term": "2019 Fall", "breadths": [1], "meeting_sections": []}