{"id": "LAT441H1F20199", "code": "LAT441H1F", "name": "Latin Historians II", "description": "Advanced readings from one or more Latin historians.", "division": "Faculty of Arts and Science", "department": "Classics", "prerequisites": "One FCE in the LAT 300-series", "exclusions": "", "level": 400, "campus": "UTSG", "term": "2019 Fall", "breadths": [1], "meeting_sections": [{"code": "L0101", "instructors": ["C Bruun"], "times": [{"day": "TUESDAY", "start": 39600, "end": 46800, "duration": 7200, "location": "LI 205"}, {"day": "THURSDAY", "start": 39600, "end": 46800, "duration": 7200, "location": "LI 205"}], "size": 10, "enrolment": 0}]}