{"id": "LIN328H5F20199", "code": "LIN328H5F", "name": "Acoustic Phonetics", "description": "This course provides an overview of the fundamentals of acoustics, as well as the acoustic properties of vowels and consonants. Students will gain hands-on experience with primary acoustic data analysis through laboratory work, and will be exposed to classic and current research in the field. Additional topics that may be addressed include speech perception, second-language phonetics, and clinical applications. [12L, 24P]", "division": "University of Toronto Mississauga", "department": "Language Studies", "prerequisites": "LIN228H5 and LIN229H5.", "exclusions": "LIN323H1", "level": 300, "campus": "UTM", "term": "2019 Fall", "breadths": [], "meeting_sections": [{"code": "L0101", "instructors": ["J Schertz"], "times": [{"day": "TUESDAY", "start": 46800, "end": 50400, "duration": 3600, "location": "IB 260"}], "size": 45, "enrolment": 0}, {"code": "P0101", "instructors": [], "times": [{"day": "TUESDAY", "start": 50400, "end": 57600, "duration": 7200, "location": "IB 200"}], "size": 45, "enrolment": 0}]}