{"id": "MDSC21H3S20201", "code": "MDSC21H3S", "name": "Anthropology of Language and Media", "description": "Anthropology studies language and media in ways that show the impact of cultural context. This course introduces this approach and also considers the role of language and media with respect to intersecting themes: ritual, religion, gender, race/ethnicity, power, nationalism, and globalization. Class assignments deal with lectures, readings, and students' examples. Same as ANTC59H3", "division": "University of Toronto Scarborough", "department": "Dept. of Arts, Culture & Media (UTSC)", "prerequisites": "[ANTB19H3 and ANTB20H3] or [MDSA01H3 and MDSB05H3 and ACMB01H3]", "exclusions": "(MDSB02H3), (ANTB21H3), ANTC59H3", "level": 300, "campus": "UTSC", "term": "2020 Winter", "breadths": [1], "meeting_sections": [{"code": "T0002", "instructors": [], "times": [{"day": "WEDNESDAY", "start": 36000, "end": 39600, "duration": 3600, "location": "BV 359"}], "size": 11, "enrolment": 3}, {"code": "T0001", "instructors": [], "times": [{"day": "WEDNESDAY", "start": 39600, "end": 43200, "duration": 3600, "location": "AC 332"}], "size": 13, "enrolment": 6}, {"code": "L01", "instructors": ["A Paz"], "times": [{"day": "TUESDAY", "start": 39600, "end": 46800, "duration": 7200, "location": "MW 140"}], "size": 25, "enrolment": 25}]}