{"id": "MGT374H5F20199", "code": "MGT374H5F", "name": "Operations Management", "description": "Operations management is concerned with the facilities and their operation to deliver the goods and services of the organization. The course develops this theme and gives a theoretical framework for managing operations. Some of the major themes include aggregate planning, materials management, and inventory control. This course introduces students to modern quantitative and computing tools necessary for in-depth operational analysis and planning. [24L]", "division": "University of Toronto Mississauga", "department": "Management", "prerequisites": "ECO220Y5/ECO227Y5/STA256H5, STA260H5/STA218H5", "exclusions": "MGOC20H3, RSM270H1", "level": 300, "campus": "UTM", "term": "2019 Fall", "breadths": [], "meeting_sections": [{"code": "L0101", "instructors": ["D Swanston"], "times": [{"day": "WEDNESDAY", "start": 54000, "end": 61200, "duration": 7200, "location": "MN 3190"}], "size": 60, "enrolment": 0}]}