{"id": "MIE364H1S20201", "code": "MIE364H1S", "name": "Quality Control and Improvement", "description": "In manufacturing and service industries alike, quality is viewed as an important strategic tool for increasing competitiveness. Continuous quality improvement is a key factor leading to a company\u2019s success. With more emphasis on quality, the cost and the product cycle time are reduced and the communication between producer and customer is improved. The course focuses on the following topics: introduction to quality engineering, TQM, quality standards, supplier-producer relations and quality certification, costs of quality, statistical process control for long and short production runs, process capability analysis and acceptance sampling, quality certification, six sigma quality, quality improvement using designed experiments and an overview of the Taguchi Methods.", "division": "Faculty of Applied Science & Engineering", "department": "Mechanical & Industrial Engineering", "prerequisites": "MIE236H1 or equivalent", "exclusions": "", "level": 300, "campus": "UTSG", "term": "2020 Winter", "breadths": [], "meeting_sections": [{"code": "P0101", "instructors": [], "times": [{"day": "MONDAY", "start": 36000, "end": 39600, "duration": 3600, "location": "WB 255"}], "size": 37, "enrolment": 36}, {"code": "P0102", "instructors": [], "times": [{"day": "MONDAY", "start": 32400, "end": 36000, "duration": 3600, "location": "WB 255"}], "size": 37, "enrolment": 18}, {"code": "P0103", "instructors": [], "times": [{"day": "THURSDAY", "start": 54000, "end": 57600, "duration": 3600, "location": "WB 255"}], "size": 37, "enrolment": 37}, {"code": "P0104", "instructors": [], "times": [{"day": "WEDNESDAY", "start": 54000, "end": 57600, "duration": 3600, "location": "RS 303"}], "size": 37, "enrolment": 37}, {"code": "T0101", "instructors": [], "times": [{"day": "TUESDAY", "start": 54000, "end": 61200, "duration": 7200, "location": "BA 2155"}], "size": 47, "enrolment": 47}, {"code": "T0102", "instructors": [], "times": [{"day": "TUESDAY", "start": 54000, "end": 61200, "duration": 7200, "location": "BA 2195"}], "size": 47, "enrolment": 46}, {"code": "T0103", "instructors": [], "times": [{"day": "THURSDAY", "start": 32400, "end": 39600, "duration": 7200, "location": "BA 2145"}], "size": 47, "enrolment": 36}, {"code": "L0101", "instructors": ["V Makis"], "times": [{"day": "WEDNESDAY", "start": 36000, "end": 43200, "duration": 7200, "location": "BA 1130"}, {"day": "MONDAY", "start": 39600, "end": 43200, "duration": 3600, "location": "BA 1130"}], "size": 138, "enrolment": 131}]}