{"id": "RLG379H1F20199", "code": "RLG379H1F", "name": "Religions of the Silk Road", "description": "An historical introduction to the religious traditions that flourished along the Silk Road, including Zoroastrianism, Manichaeism, Nestorian Christianity, Judaism, Buddhism and Islam. Drawing on a variety of sources (textual, archaeological, works of art), the course will focus on the spread and development of these traditions through the medieval period. Issues include cross-cultural exchange, religious syncretism, ethnic identity formation and so on. Emphasis will also be placed on religious and political events in modern Central Asia.", "division": "Faculty of Arts and Science", "department": "Department for the Study of Religion", "prerequisites": "Completion of 4.0 credits", "exclusions": "RLG245H1", "level": 300, "campus": "UTSG", "term": "2019 Fall", "breadths": [2], "meeting_sections": [{"code": "L0101", "instructors": ["A Goodman"], "times": [{"day": "MONDAY", "start": 43200, "end": 50400, "duration": 7200, "location": "WI 523"}], "size": 50, "enrolment": 0}]}