{"id": "RLG454H1F20199", "code": "RLG454H1F", "name": "Social History of the Jesus Movement", "description": "The social setting of the early Jesus movement in Roman Palestine and the cities of the Eastern Empire. Topics will include: rank and legal status; patronalia and clientalia; marriage and divorce; forms of association outside the family; slavery and manumission; loyalty to the empire and forms of resistance.", "division": "Faculty of Arts and Science", "department": "Department for the Study of Religion", "prerequisites": "RLG241Y1 or RLG241H1, and at least one of RLG320H1/RLG321H1/RLG322H1/RLG323H1/RLG324H1/RLG325H1/RLG326H1, and permission of instructor", "exclusions": "", "level": 400, "campus": "UTSG", "term": "2019 Fall", "breadths": [3], "meeting_sections": [{"code": "L0101", "instructors": ["J Kloppenborg"], "times": [{"day": "THURSDAY", "start": 32400, "end": 43200, "duration": 10800, "location": "JH 214"}], "size": 5, "enrolment": 0}]}