{"id": "SMC430H1S20201", "code": "SMC430H1S", "name": "Advanced Topics in Book and Media Studies I", "description": "A course/seminar on a topic to be determined annually.", "division": "Faculty of Arts and Science", "department": "St. Michael's College", "prerequisites": "", "exclusions": "", "level": 400, "campus": "UTSG", "term": "2020 Winter", "breadths": [], "meeting_sections": [{"code": "L0101", "instructors": ["F Parker"], "times": [{"day": "TUESDAY", "start": 46800, "end": 57600, "duration": 10800, "location": "AH 302"}], "size": 30, "enrolment": 30}]}