{"id": "SOC327H5F20199", "code": "SOC327H5F", "name": "Drugs and the Modern World", "description": "The course examines how \"drugs\", as well as attempts to police and control their use, have been implicated in the making of the modern world. Instead of taking drugs as inherently criminal and deviant, the course will look at how drugs have played a central role in the development of capitalism, colonialism and global inequality in the past 200 years. [24L]", "division": "University of Toronto Mississauga", "department": "Sociology", "prerequisites": "SOC205H5/SOC231H5, SOC209H5, SOC221H5, SOC222H5", "exclusions": "", "level": 300, "campus": "UTM", "term": "2019 Fall", "breadths": [], "meeting_sections": [{"code": "L0101", "instructors": ["L Farah Schwartzman"], "times": [{"day": "FRIDAY", "start": 39600, "end": 46800, "duration": 7200, "location": "MN 3190"}], "size": 60, "enrolment": 0}]}