{"id": "VIS204H1F20199", "code": "VIS204H1F", "name": "Installation Art", "description": "This course introduces students to the basic principles of working with materials to produce three-dimensional and installation-based artworks. This hands-on project-based course includes individual and group critiques, seminars with relevant readings and critical viewing of contemporary installation artworks.", "division": "John H. Daniels Faculty of Architecture, Landscape, & Design", "department": "John H. Daniels Faculty of Architecture, Landscape, & Design", "prerequisites": "JAV130H1/ VIS130H1", "exclusions": "FAS248H5", "level": 200, "campus": "UTSG", "term": "2019 Fall", "breadths": [], "meeting_sections": [{"code": "P0101", "instructors": ["C Telford-Keogh"], "times": [{"day": "TUESDAY", "start": 32400, "end": 43200, "duration": 10800, "location": "NB 106"}], "size": 20, "enrolment": 0}]}