{"id": "VPSB80H3S20201", "code": "VPSB80H3S", "name": "Digital Studio II", "description": "An in-depth investigation of digital imaging technologies for serious studio artists and new media designers. Emphasis is placed on advanced image manipulation, seamless collage, invisible retouching and quality control techniques for fine art production. Project themes will be drawn from a critical analysis of contemporary painting and photo-based art.", "division": "University of Toronto Scarborough", "department": "Dept. of Arts, Culture & Media (UTSC)", "prerequisites": "VPSB56H3", "exclusions": "FAS247H, VIS318H", "level": 200, "campus": "UTSC", "term": "2020 Winter", "breadths": [1], "meeting_sections": [{"code": "L01", "instructors": ["J Lujan"], "times": [{"day": "TUESDAY", "start": 36000, "end": 46800, "duration": 10800, "location": "BV 494"}], "size": 20, "enrolment": 20}]}